[
    {
        "%vlocity_namespace%__AttributeCategoryId__c": {
            "%vlocity_namespace%__Code__c": "B2CCmex_ATC_CHARACTERISTIC",
            "VlocityDataPackType": "VlocityLookupMatchingKeyObject",
            "VlocityLookupRecordSourceKey": "%vlocity_namespace%__AttributeCategory__c/B2CCmex_ATC_CHARACTERISTIC",
            "VlocityRecordSObjectType": "%vlocity_namespace%__AttributeCategory__c"
        },
        "%vlocity_namespace%__AttributeId__c": {
            "%vlocity_namespace%__Code__c": "B2CCmex_ATTR_DATA_CHAR",
            "VlocityDataPackType": "VlocityLookupMatchingKeyObject",
            "VlocityLookupRecordSourceKey": "%vlocity_namespace%__Attribute__c/B2CCmex_ATTR_DATA_CHAR",
            "VlocityRecordSObjectType": "%vlocity_namespace%__Attribute__c"
        },
        "%vlocity_namespace%__GlobalKey__c": "3f45ad93-b318-1e53-cd2e-a7e2c7044195",
        "%vlocity_namespace%__IsActive__c": true,
        "%vlocity_namespace%__ObjectClassId__c": {
            "%vlocity_namespace%__GlobalKey__c": "63ba6ae5f8c257f7cdccc385d2a85dca",
            "VlocityDataPackType": "VlocityLookupMatchingKeyObject",
            "VlocityLookupRecordSourceKey": "%vlocity_namespace%__ObjectClass__c/63ba6ae5f8c257f7cdccc385d2a85dca",
            "VlocityRecordSObjectType": "%vlocity_namespace%__ObjectClass__c"
        },
        "%vlocity_namespace%__ObjectType__c": "Product2",
        "%vlocity_namespace%__SubClassId__c": {
            "%vlocity_namespace%__GlobalKey__c": "8ad6f687-56aa-9ccd-bbc3-5f01214018d2",
            "VlocityDataPackType": "VlocityMatchingKeyObject",
            "VlocityMatchingRecordSourceKey": "Product2/8ad6f687-56aa-9ccd-bbc3-5f01214018d2",
            "VlocityRecordSObjectType": "Product2"
        },
        "Name": "3f45ad93-b318-1e53-cd2e-a7e2c7044195",
        "VlocityDataPackType": "SObject",
        "VlocityRecordSObjectType": "%vlocity_namespace%__ObjectFieldAttribute__c"
    },
    {
        "%vlocity_namespace%__AttributeCategoryId__c": {
            "%vlocity_namespace%__Code__c": "B2CCmex_ATC_CHARACTERISTIC",
            "VlocityDataPackType": "VlocityLookupMatchingKeyObject",
            "VlocityLookupRecordSourceKey": "%vlocity_namespace%__AttributeCategory__c/B2CCmex_ATC_CHARACTERISTIC",
            "VlocityRecordSObjectType": "%vlocity_namespace%__AttributeCategory__c"
        },
        "%vlocity_namespace%__AttributeId__c": {
            "%vlocity_namespace%__Code__c": "B2CCmex_ATTR_HASDISCOUNT_CHAR",
            "VlocityDataPackType": "VlocityLookupMatchingKeyObject",
            "VlocityLookupRecordSourceKey": "%vlocity_namespace%__Attribute__c/B2CCmex_ATTR_HASDISCOUNT_CHAR",
            "VlocityRecordSObjectType": "%vlocity_namespace%__Attribute__c"
        },
        "%vlocity_namespace%__GlobalKey__c": "9ceef948-1457-a1ce-6634-4ffb90474b2f",
        "%vlocity_namespace%__IsActive__c": true,
        "%vlocity_namespace%__ObjectClassId__c": {
            "%vlocity_namespace%__GlobalKey__c": "63ba6ae5f8c257f7cdccc385d2a85dca",
            "VlocityDataPackType": "VlocityLookupMatchingKeyObject",
            "VlocityLookupRecordSourceKey": "%vlocity_namespace%__ObjectClass__c/63ba6ae5f8c257f7cdccc385d2a85dca",
            "VlocityRecordSObjectType": "%vlocity_namespace%__ObjectClass__c"
        },
        "%vlocity_namespace%__ObjectType__c": "Product2",
        "%vlocity_namespace%__SubClassId__c": {
            "%vlocity_namespace%__GlobalKey__c": "8ad6f687-56aa-9ccd-bbc3-5f01214018d2",
            "VlocityDataPackType": "VlocityMatchingKeyObject",
            "VlocityMatchingRecordSourceKey": "Product2/8ad6f687-56aa-9ccd-bbc3-5f01214018d2",
            "VlocityRecordSObjectType": "Product2"
        },
        "Name": "9ceef948-1457-a1ce-6634-4ffb90474b2f",
        "VlocityDataPackType": "SObject",
        "VlocityRecordSObjectType": "%vlocity_namespace%__ObjectFieldAttribute__c"
    },
    {
        "%vlocity_namespace%__AttributeCategoryId__c": {
            "%vlocity_namespace%__Code__c": "B2CCmex_ATC_CHARACTERISTIC",
            "VlocityDataPackType": "VlocityLookupMatchingKeyObject",
            "VlocityLookupRecordSourceKey": "%vlocity_namespace%__AttributeCategory__c/B2CCmex_ATC_CHARACTERISTIC",
            "VlocityRecordSObjectType": "%vlocity_namespace%__AttributeCategory__c"
        },
        "%vlocity_namespace%__AttributeId__c": {
            "%vlocity_namespace%__Code__c": "B2CCmex_ATTR_MMS",
            "VlocityDataPackType": "VlocityLookupMatchingKeyObject",
            "VlocityLookupRecordSourceKey": "%vlocity_namespace%__Attribute__c/B2CCmex_ATTR_MMS",
            "VlocityRecordSObjectType": "%vlocity_namespace%__Attribute__c"
        },
        "%vlocity_namespace%__GlobalKey__c": "b6c8f03b-893f-6d37-7051-68a24f3e4125",
        "%vlocity_namespace%__IsActive__c": true,
        "%vlocity_namespace%__ObjectClassId__c": {
            "%vlocity_namespace%__GlobalKey__c": "63ba6ae5f8c257f7cdccc385d2a85dca",
            "VlocityDataPackType": "VlocityLookupMatchingKeyObject",
            "VlocityLookupRecordSourceKey": "%vlocity_namespace%__ObjectClass__c/63ba6ae5f8c257f7cdccc385d2a85dca",
            "VlocityRecordSObjectType": "%vlocity_namespace%__ObjectClass__c"
        },
        "%vlocity_namespace%__ObjectType__c": "Product2",
        "%vlocity_namespace%__SubClassId__c": {
            "%vlocity_namespace%__GlobalKey__c": "8ad6f687-56aa-9ccd-bbc3-5f01214018d2",
            "VlocityDataPackType": "VlocityMatchingKeyObject",
            "VlocityMatchingRecordSourceKey": "Product2/8ad6f687-56aa-9ccd-bbc3-5f01214018d2",
            "VlocityRecordSObjectType": "Product2"
        },
        "Name": "b6c8f03b-893f-6d37-7051-68a24f3e4125",
        "VlocityDataPackType": "SObject",
        "VlocityRecordSObjectType": "%vlocity_namespace%__ObjectFieldAttribute__c"
    },
    {
        "%vlocity_namespace%__AttributeCategoryId__c": {
            "%vlocity_namespace%__Code__c": "B2CCmex_ATC_CHARACTERISTIC",
            "VlocityDataPackType": "VlocityLookupMatchingKeyObject",
            "VlocityLookupRecordSourceKey": "%vlocity_namespace%__AttributeCategory__c/B2CCmex_ATC_CHARACTERISTIC",
            "VlocityRecordSObjectType": "%vlocity_namespace%__AttributeCategory__c"
        },
        "%vlocity_namespace%__AttributeId__c": {
            "%vlocity_namespace%__Code__c": "B2CCmex_ATTR_PAYMENT_OPTION_CHAR",
            "VlocityDataPackType": "VlocityLookupMatchingKeyObject",
            "VlocityLookupRecordSourceKey": "%vlocity_namespace%__Attribute__c/B2CCmex_ATTR_PAYMENT_OPTION_CHAR",
            "VlocityRecordSObjectType": "%vlocity_namespace%__Attribute__c"
        },
        "%vlocity_namespace%__GlobalKey__c": "d15dbbcf-dfaf-af1b-020e-e5bcae4281d1",
        "%vlocity_namespace%__IsActive__c": true,
        "%vlocity_namespace%__ObjectClassId__c": {
            "%vlocity_namespace%__GlobalKey__c": "63ba6ae5f8c257f7cdccc385d2a85dca",
            "VlocityDataPackType": "VlocityLookupMatchingKeyObject",
            "VlocityLookupRecordSourceKey": "%vlocity_namespace%__ObjectClass__c/63ba6ae5f8c257f7cdccc385d2a85dca",
            "VlocityRecordSObjectType": "%vlocity_namespace%__ObjectClass__c"
        },
        "%vlocity_namespace%__ObjectType__c": "Product2",
        "%vlocity_namespace%__SubClassId__c": {
            "%vlocity_namespace%__GlobalKey__c": "8ad6f687-56aa-9ccd-bbc3-5f01214018d2",
            "VlocityDataPackType": "VlocityMatchingKeyObject",
            "VlocityMatchingRecordSourceKey": "Product2/8ad6f687-56aa-9ccd-bbc3-5f01214018d2",
            "VlocityRecordSObjectType": "Product2"
        },
        "Name": "d15dbbcf-dfaf-af1b-020e-e5bcae4281d1",
        "VlocityDataPackType": "SObject",
        "VlocityRecordSObjectType": "%vlocity_namespace%__ObjectFieldAttribute__c"
    },
    {
        "%vlocity_namespace%__AttributeCategoryId__c": {
            "%vlocity_namespace%__Code__c": "B2CCmex_ATC_CHARACTERISTIC",
            "VlocityDataPackType": "VlocityLookupMatchingKeyObject",
            "VlocityLookupRecordSourceKey": "%vlocity_namespace%__AttributeCategory__c/B2CCmex_ATC_CHARACTERISTIC",
            "VlocityRecordSObjectType": "%vlocity_namespace%__AttributeCategory__c"
        },
        "%vlocity_namespace%__AttributeId__c": {
            "%vlocity_namespace%__Code__c": "B2CCmex_ATTR_SMS_CHAR",
            "VlocityDataPackType": "VlocityLookupMatchingKeyObject",
            "VlocityLookupRecordSourceKey": "%vlocity_namespace%__Attribute__c/B2CCmex_ATTR_SMS_CHAR",
            "VlocityRecordSObjectType": "%vlocity_namespace%__Attribute__c"
        },
        "%vlocity_namespace%__GlobalKey__c": "34a13abb-d5ca-99a8-9fb4-0d682be775ab",
        "%vlocity_namespace%__IsActive__c": true,
        "%vlocity_namespace%__ObjectClassId__c": {
            "%vlocity_namespace%__GlobalKey__c": "63ba6ae5f8c257f7cdccc385d2a85dca",
            "VlocityDataPackType": "VlocityLookupMatchingKeyObject",
            "VlocityLookupRecordSourceKey": "%vlocity_namespace%__ObjectClass__c/63ba6ae5f8c257f7cdccc385d2a85dca",
            "VlocityRecordSObjectType": "%vlocity_namespace%__ObjectClass__c"
        },
        "%vlocity_namespace%__ObjectType__c": "Product2",
        "%vlocity_namespace%__SubClassId__c": {
            "%vlocity_namespace%__GlobalKey__c": "8ad6f687-56aa-9ccd-bbc3-5f01214018d2",
            "VlocityDataPackType": "VlocityMatchingKeyObject",
            "VlocityMatchingRecordSourceKey": "Product2/8ad6f687-56aa-9ccd-bbc3-5f01214018d2",
            "VlocityRecordSObjectType": "Product2"
        },
        "Name": "34a13abb-d5ca-99a8-9fb4-0d682be775ab",
        "VlocityDataPackType": "SObject",
        "VlocityRecordSObjectType": "%vlocity_namespace%__ObjectFieldAttribute__c"
    },
    {
        "%vlocity_namespace%__AttributeCategoryId__c": {
            "%vlocity_namespace%__Code__c": "B2CCmex_ATC_CHARACTERISTIC",
            "VlocityDataPackType": "VlocityLookupMatchingKeyObject",
            "VlocityLookupRecordSourceKey": "%vlocity_namespace%__AttributeCategory__c/B2CCmex_ATC_CHARACTERISTIC",
            "VlocityRecordSObjectType": "%vlocity_namespace%__AttributeCategory__c"
        },
        "%vlocity_namespace%__AttributeId__c": {
            "%vlocity_namespace%__Code__c": "B2CCmex_ATTR_TANGIBLE_CHAR",
            "VlocityDataPackType": "VlocityLookupMatchingKeyObject",
            "VlocityLookupRecordSourceKey": "%vlocity_namespace%__Attribute__c/B2CCmex_ATTR_TANGIBLE_CHAR",
            "VlocityRecordSObjectType": "%vlocity_namespace%__Attribute__c"
        },
        "%vlocity_namespace%__GlobalKey__c": "53fbe2aa-c82c-7ef9-179b-aa33a08f5c60",
        "%vlocity_namespace%__IsActive__c": true,
        "%vlocity_namespace%__ObjectClassId__c": {
            "%vlocity_namespace%__GlobalKey__c": "63ba6ae5f8c257f7cdccc385d2a85dca",
            "VlocityDataPackType": "VlocityLookupMatchingKeyObject",
            "VlocityLookupRecordSourceKey": "%vlocity_namespace%__ObjectClass__c/63ba6ae5f8c257f7cdccc385d2a85dca",
            "VlocityRecordSObjectType": "%vlocity_namespace%__ObjectClass__c"
        },
        "%vlocity_namespace%__ObjectType__c": "Product2",
        "%vlocity_namespace%__SubClassId__c": {
            "%vlocity_namespace%__GlobalKey__c": "8ad6f687-56aa-9ccd-bbc3-5f01214018d2",
            "VlocityDataPackType": "VlocityMatchingKeyObject",
            "VlocityMatchingRecordSourceKey": "Product2/8ad6f687-56aa-9ccd-bbc3-5f01214018d2",
            "VlocityRecordSObjectType": "Product2"
        },
        "Name": "53fbe2aa-c82c-7ef9-179b-aa33a08f5c60",
        "VlocityDataPackType": "SObject",
        "VlocityRecordSObjectType": "%vlocity_namespace%__ObjectFieldAttribute__c"
    },
    {
        "%vlocity_namespace%__AttributeCategoryId__c": {
            "%vlocity_namespace%__Code__c": "B2CCmex_ATC_CHARACTERISTIC",
            "VlocityDataPackType": "VlocityLookupMatchingKeyObject",
            "VlocityLookupRecordSourceKey": "%vlocity_namespace%__AttributeCategory__c/B2CCmex_ATC_CHARACTERISTIC",
            "VlocityRecordSObjectType": "%vlocity_namespace%__AttributeCategory__c"
        },
        "%vlocity_namespace%__AttributeId__c": {
            "%vlocity_namespace%__Code__c": "B2CCmex_ATTR_VOICE_CHAR",
            "VlocityDataPackType": "VlocityLookupMatchingKeyObject",
            "VlocityLookupRecordSourceKey": "%vlocity_namespace%__Attribute__c/B2CCmex_ATTR_VOICE_CHAR",
            "VlocityRecordSObjectType": "%vlocity_namespace%__Attribute__c"
        },
        "%vlocity_namespace%__GlobalKey__c": "bcba6653-674c-8600-2861-8c7d9bff7260",
        "%vlocity_namespace%__IsActive__c": true,
        "%vlocity_namespace%__ObjectClassId__c": {
            "%vlocity_namespace%__GlobalKey__c": "63ba6ae5f8c257f7cdccc385d2a85dca",
            "VlocityDataPackType": "VlocityLookupMatchingKeyObject",
            "VlocityLookupRecordSourceKey": "%vlocity_namespace%__ObjectClass__c/63ba6ae5f8c257f7cdccc385d2a85dca",
            "VlocityRecordSObjectType": "%vlocity_namespace%__ObjectClass__c"
        },
        "%vlocity_namespace%__ObjectType__c": "Product2",
        "%vlocity_namespace%__SubClassId__c": {
            "%vlocity_namespace%__GlobalKey__c": "8ad6f687-56aa-9ccd-bbc3-5f01214018d2",
            "VlocityDataPackType": "VlocityMatchingKeyObject",
            "VlocityMatchingRecordSourceKey": "Product2/8ad6f687-56aa-9ccd-bbc3-5f01214018d2",
            "VlocityRecordSObjectType": "Product2"
        },
        "Name": "bcba6653-674c-8600-2861-8c7d9bff7260",
        "VlocityDataPackType": "SObject",
        "VlocityRecordSObjectType": "%vlocity_namespace%__ObjectFieldAttribute__c"
    }
]