[
    {
        "%vlocity_namespace%__CompiledAttributeOverrideId__c": {
            "VlocityDataPackType": "VlocityMatchingKeyObject",
            "VlocityMatchingRecordSourceKey": "%vlocity_namespace%__CompiledAttributeOverride__c/Generated394847861",
            "VlocityRecordSObjectType": "%vlocity_namespace%__CompiledAttributeOverride__c"
        },
        "%vlocity_namespace%__IsExclude__c": false,
        "%vlocity_namespace%__OverriddenAttributeAssignmentCategoryId__c": {
            "%vlocity_namespace%__Code__c": "B2CCmex_ATC_INTERNET_DETAILS",
            "VlocityDataPackType": "VlocityLookupMatchingKeyObject",
            "VlocityLookupRecordSourceKey": "%vlocity_namespace%__AttributeCategory__c/B2CCmex_ATC_INTERNET_DETAILS",
            "VlocityRecordSObjectType": "%vlocity_namespace%__AttributeCategory__c"
        },
        "%vlocity_namespace%__OverriddenAttributeAssignmentId__c": {
            "%vlocity_namespace%__AttributeId__r.%vlocity_namespace%__Code__c": "B2CCmex_ATTR_DOWNLOAD_SPEED",
            "%vlocity_namespace%__IsOverride__c": false,
            "%vlocity_namespace%__ObjectId__c": {
                "%vlocity_namespace%__GlobalKey__c": "24025f47-e7d0-24e5-1fb5-7b7b5894cd63",
                "VlocityDataPackType": "VlocityLookupMatchingKeyObject",
                "VlocityLookupRecordSourceKey": "Product2/24025f47-e7d0-24e5-1fb5-7b7b5894cd63",
                "VlocityRecordSObjectType": "Product2"
            },
            "%vlocity_namespace%__OverrideContext__c": null,
            "VlocityDataPackType": "VlocityLookupMatchingKeyObject",
            "VlocityLookupRecordSourceKey": "%vlocity_namespace%__AttributeAssignment__c/fe4d794a-08ea-0c41-6b53-4b6b87f3d44b",
            "VlocityRecordSObjectType": "%vlocity_namespace%__AttributeAssignment__c"
        },
        "%vlocity_namespace%__OverrideType__c": "Attribute",
        "%vlocity_namespace%__OverridingAttributeAssignmentCategoryId__c": {
            "%vlocity_namespace%__Code__c": "B2CCmex_ATC_INTERNET_DETAILS",
            "VlocityDataPackType": "VlocityLookupMatchingKeyObject",
            "VlocityLookupRecordSourceKey": "%vlocity_namespace%__AttributeCategory__c/B2CCmex_ATC_INTERNET_DETAILS",
            "VlocityRecordSObjectType": "%vlocity_namespace%__AttributeCategory__c"
        },
        "%vlocity_namespace%__OverridingAttributeAssignmentId__c": {
            "%vlocity_namespace%__AttributeId__r.%vlocity_namespace%__Code__c": "B2CCmex_ATTR_DOWNLOAD_SPEED",
            "%vlocity_namespace%__IsOverride__c": true,
            "%vlocity_namespace%__ObjectId__c": {
                "%vlocity_namespace%__GlobalKey__c": "24025f47-e7d0-24e5-1fb5-7b7b5894cd63",
                "VlocityDataPackType": "VlocityLookupMatchingKeyObject",
                "VlocityLookupRecordSourceKey": "Product2/24025f47-e7d0-24e5-1fb5-7b7b5894cd63",
                "VlocityRecordSObjectType": "Product2"
            },
            "%vlocity_namespace%__OverrideContext__c": "3544171306",
            "VlocityDataPackType": "VlocityLookupMatchingKeyObject",
            "VlocityLookupRecordSourceKey": "%vlocity_namespace%__AttributeAssignment__c/09e278f6-4fd9-3665-7084-50d1701969cb",
            "VlocityRecordSObjectType": "%vlocity_namespace%__AttributeAssignment__c"
        },
        "%vlocity_namespace%__ProductGroupKey__c": "0ddf26a1-085e-d1c1-980d-12697edeba22",
        "%vlocity_namespace%__ProductHierarchyGlobalKeyPath__c": "7269d563-a88c-243a-e898-60383002e162<004e0927-0f26-6c5c-595c-50f2df58f16c<24025f47-e7d0-24e5-1fb5-7b7b5894cd63",
        "%vlocity_namespace%__ProductHierarchyGroupKeyPath__c": "0ddf26a1-085e-d1c1-980d-12697edeba22<9dd6a408-253f-4bf8-0fe9-8870d20b7764<bdea6cdf-93b7-8017-af65-d5dc1d568b91",
        "%vlocity_namespace%__ProductHierarchyPath__c": "01t4U000003MtcAQAS<01t4U000003MtZNQA0<01t4U000003MtWeQAK",
        "%vlocity_namespace%__ProductId__c": {
            "%vlocity_namespace%__GlobalKey__c": "7269d563-a88c-243a-e898-60383002e162",
            "VlocityDataPackType": "VlocityMatchingKeyObject",
            "VlocityMatchingRecordSourceKey": "Product2/7269d563-a88c-243a-e898-60383002e162",
            "VlocityRecordSObjectType": "Product2"
        },
        "Name": "OverrideDefinition",
        "VlocityDataPackType": "SObject",
        "VlocityRecordSObjectType": "%vlocity_namespace%__OverrideDefinition__c"
    },
    {
        "%vlocity_namespace%__CompiledAttributeOverrideId__c": {
            "VlocityDataPackType": "VlocityMatchingKeyObject",
            "VlocityMatchingRecordSourceKey": "%vlocity_namespace%__CompiledAttributeOverride__c/Generated394847861",
            "VlocityRecordSObjectType": "%vlocity_namespace%__CompiledAttributeOverride__c"
        },
        "%vlocity_namespace%__IsExclude__c": false,
        "%vlocity_namespace%__OverriddenAttributeAssignmentCategoryId__c": {
            "%vlocity_namespace%__Code__c": "B2CCmex_ATC_INTERNET_DETAILS",
            "VlocityDataPackType": "VlocityLookupMatchingKeyObject",
            "VlocityLookupRecordSourceKey": "%vlocity_namespace%__AttributeCategory__c/B2CCmex_ATC_INTERNET_DETAILS",
            "VlocityRecordSObjectType": "%vlocity_namespace%__AttributeCategory__c"
        },
        "%vlocity_namespace%__OverriddenAttributeAssignmentId__c": {
            "%vlocity_namespace%__AttributeId__r.%vlocity_namespace%__Code__c": "B2CCmex_ATTR_MONTHLY_DATA_CAP",
            "%vlocity_namespace%__IsOverride__c": false,
            "%vlocity_namespace%__ObjectId__c": {
                "%vlocity_namespace%__GlobalKey__c": "24025f47-e7d0-24e5-1fb5-7b7b5894cd63",
                "VlocityDataPackType": "VlocityLookupMatchingKeyObject",
                "VlocityLookupRecordSourceKey": "Product2/24025f47-e7d0-24e5-1fb5-7b7b5894cd63",
                "VlocityRecordSObjectType": "Product2"
            },
            "%vlocity_namespace%__OverrideContext__c": null,
            "VlocityDataPackType": "VlocityLookupMatchingKeyObject",
            "VlocityLookupRecordSourceKey": "%vlocity_namespace%__AttributeAssignment__c/5764d99e-6621-d267-1533-cbed616fa605",
            "VlocityRecordSObjectType": "%vlocity_namespace%__AttributeAssignment__c"
        },
        "%vlocity_namespace%__OverrideType__c": "Attribute",
        "%vlocity_namespace%__OverridingAttributeAssignmentCategoryId__c": {
            "%vlocity_namespace%__Code__c": "B2CCmex_ATC_INTERNET_DETAILS",
            "VlocityDataPackType": "VlocityLookupMatchingKeyObject",
            "VlocityLookupRecordSourceKey": "%vlocity_namespace%__AttributeCategory__c/B2CCmex_ATC_INTERNET_DETAILS",
            "VlocityRecordSObjectType": "%vlocity_namespace%__AttributeCategory__c"
        },
        "%vlocity_namespace%__OverridingAttributeAssignmentId__c": {
            "%vlocity_namespace%__AttributeId__r.%vlocity_namespace%__Code__c": "B2CCmex_ATTR_MONTHLY_DATA_CAP",
            "%vlocity_namespace%__IsOverride__c": true,
            "%vlocity_namespace%__ObjectId__c": {
                "%vlocity_namespace%__GlobalKey__c": "24025f47-e7d0-24e5-1fb5-7b7b5894cd63",
                "VlocityDataPackType": "VlocityLookupMatchingKeyObject",
                "VlocityLookupRecordSourceKey": "Product2/24025f47-e7d0-24e5-1fb5-7b7b5894cd63",
                "VlocityRecordSObjectType": "Product2"
            },
            "%vlocity_namespace%__OverrideContext__c": "3544171306",
            "VlocityDataPackType": "VlocityLookupMatchingKeyObject",
            "VlocityLookupRecordSourceKey": "%vlocity_namespace%__AttributeAssignment__c/9301f9a6-1afb-444e-83d0-206de9931e76",
            "VlocityRecordSObjectType": "%vlocity_namespace%__AttributeAssignment__c"
        },
        "%vlocity_namespace%__ProductGroupKey__c": "0ddf26a1-085e-d1c1-980d-12697edeba22",
        "%vlocity_namespace%__ProductHierarchyGlobalKeyPath__c": "7269d563-a88c-243a-e898-60383002e162<004e0927-0f26-6c5c-595c-50f2df58f16c<24025f47-e7d0-24e5-1fb5-7b7b5894cd63",
        "%vlocity_namespace%__ProductHierarchyGroupKeyPath__c": "0ddf26a1-085e-d1c1-980d-12697edeba22<9dd6a408-253f-4bf8-0fe9-8870d20b7764<bdea6cdf-93b7-8017-af65-d5dc1d568b91",
        "%vlocity_namespace%__ProductHierarchyPath__c": "01t4U000003MtcAQAS<01t4U000003MtZNQA0<01t4U000003MtWeQAK",
        "%vlocity_namespace%__ProductId__c": {
            "%vlocity_namespace%__GlobalKey__c": "7269d563-a88c-243a-e898-60383002e162",
            "VlocityDataPackType": "VlocityMatchingKeyObject",
            "VlocityMatchingRecordSourceKey": "Product2/7269d563-a88c-243a-e898-60383002e162",
            "VlocityRecordSObjectType": "Product2"
        },
        "Name": "OverrideDefinition",
        "VlocityDataPackType": "SObject",
        "VlocityRecordSObjectType": "%vlocity_namespace%__OverrideDefinition__c"
    },
    {
        "%vlocity_namespace%__CompiledAttributeOverrideId__c": {
            "VlocityDataPackType": "VlocityMatchingKeyObject",
            "VlocityMatchingRecordSourceKey": "%vlocity_namespace%__CompiledAttributeOverride__c/Generated394847861",
            "VlocityRecordSObjectType": "%vlocity_namespace%__CompiledAttributeOverride__c"
        },
        "%vlocity_namespace%__IsExclude__c": false,
        "%vlocity_namespace%__OverriddenAttributeAssignmentCategoryId__c": {
            "%vlocity_namespace%__Code__c": "B2CCmex_ATC_INTERNET_DETAILS",
            "VlocityDataPackType": "VlocityLookupMatchingKeyObject",
            "VlocityLookupRecordSourceKey": "%vlocity_namespace%__AttributeCategory__c/B2CCmex_ATC_INTERNET_DETAILS",
            "VlocityRecordSObjectType": "%vlocity_namespace%__AttributeCategory__c"
        },
        "%vlocity_namespace%__OverriddenAttributeAssignmentId__c": {
            "%vlocity_namespace%__AttributeId__r.%vlocity_namespace%__Code__c": "B2CCmex_ATTR_UPLOAD_SPEED",
            "%vlocity_namespace%__IsOverride__c": false,
            "%vlocity_namespace%__ObjectId__c": {
                "%vlocity_namespace%__GlobalKey__c": "24025f47-e7d0-24e5-1fb5-7b7b5894cd63",
                "VlocityDataPackType": "VlocityLookupMatchingKeyObject",
                "VlocityLookupRecordSourceKey": "Product2/24025f47-e7d0-24e5-1fb5-7b7b5894cd63",
                "VlocityRecordSObjectType": "Product2"
            },
            "%vlocity_namespace%__OverrideContext__c": null,
            "VlocityDataPackType": "VlocityLookupMatchingKeyObject",
            "VlocityLookupRecordSourceKey": "%vlocity_namespace%__AttributeAssignment__c/27b33492-88c3-a8f3-79bb-eee0d7905029",
            "VlocityRecordSObjectType": "%vlocity_namespace%__AttributeAssignment__c"
        },
        "%vlocity_namespace%__OverrideType__c": "Attribute",
        "%vlocity_namespace%__OverridingAttributeAssignmentCategoryId__c": {
            "%vlocity_namespace%__Code__c": "B2CCmex_ATC_INTERNET_DETAILS",
            "VlocityDataPackType": "VlocityLookupMatchingKeyObject",
            "VlocityLookupRecordSourceKey": "%vlocity_namespace%__AttributeCategory__c/B2CCmex_ATC_INTERNET_DETAILS",
            "VlocityRecordSObjectType": "%vlocity_namespace%__AttributeCategory__c"
        },
        "%vlocity_namespace%__OverridingAttributeAssignmentId__c": {
            "%vlocity_namespace%__AttributeId__r.%vlocity_namespace%__Code__c": "B2CCmex_ATTR_UPLOAD_SPEED",
            "%vlocity_namespace%__IsOverride__c": true,
            "%vlocity_namespace%__ObjectId__c": {
                "%vlocity_namespace%__GlobalKey__c": "24025f47-e7d0-24e5-1fb5-7b7b5894cd63",
                "VlocityDataPackType": "VlocityLookupMatchingKeyObject",
                "VlocityLookupRecordSourceKey": "Product2/24025f47-e7d0-24e5-1fb5-7b7b5894cd63",
                "VlocityRecordSObjectType": "Product2"
            },
            "%vlocity_namespace%__OverrideContext__c": "3544171306",
            "VlocityDataPackType": "VlocityLookupMatchingKeyObject",
            "VlocityLookupRecordSourceKey": "%vlocity_namespace%__AttributeAssignment__c/1a5af49e-63be-a559-d4ce-89a79a484f3a",
            "VlocityRecordSObjectType": "%vlocity_namespace%__AttributeAssignment__c"
        },
        "%vlocity_namespace%__ProductGroupKey__c": "0ddf26a1-085e-d1c1-980d-12697edeba22",
        "%vlocity_namespace%__ProductHierarchyGlobalKeyPath__c": "7269d563-a88c-243a-e898-60383002e162<004e0927-0f26-6c5c-595c-50f2df58f16c<24025f47-e7d0-24e5-1fb5-7b7b5894cd63",
        "%vlocity_namespace%__ProductHierarchyGroupKeyPath__c": "0ddf26a1-085e-d1c1-980d-12697edeba22<9dd6a408-253f-4bf8-0fe9-8870d20b7764<bdea6cdf-93b7-8017-af65-d5dc1d568b91",
        "%vlocity_namespace%__ProductHierarchyPath__c": "01t4U000003MtcAQAS<01t4U000003MtZNQA0<01t4U000003MtWeQAK",
        "%vlocity_namespace%__ProductId__c": {
            "%vlocity_namespace%__GlobalKey__c": "7269d563-a88c-243a-e898-60383002e162",
            "VlocityDataPackType": "VlocityMatchingKeyObject",
            "VlocityMatchingRecordSourceKey": "Product2/7269d563-a88c-243a-e898-60383002e162",
            "VlocityRecordSObjectType": "Product2"
        },
        "Name": "OverrideDefinition",
        "VlocityDataPackType": "SObject",
        "VlocityRecordSObjectType": "%vlocity_namespace%__OverrideDefinition__c"
    }
]