[
    {
        "%vlocity_namespace%__AddDate__c": "",
        "%vlocity_namespace%__AttributeAdjustmentComments__c": "",
        "%vlocity_namespace%__AttributeAdjustmentUnits__c": "",
        "%vlocity_namespace%__AttributeCategoryId__c": {
            "%vlocity_namespace%__Code__c": "B2CCmex_ATC_CHARACTERISTIC",
            "VlocityDataPackType": "VlocityLookupMatchingKeyObject",
            "VlocityLookupRecordSourceKey": "%vlocity_namespace%__AttributeCategory__c/B2CCmex_ATC_CHARACTERISTIC",
            "VlocityRecordSObjectType": "%vlocity_namespace%__AttributeCategory__c"
        },
        "%vlocity_namespace%__AttributeDisplayNameOverride__c": "HasDiscount",
        "%vlocity_namespace%__AttributeDisplaySequence__c": "27",
        "%vlocity_namespace%__AttributeId__c": {
            "%vlocity_namespace%__Code__c": "B2CCmex_ATTR_HASDISCOUNT_CHAR",
            "VlocityDataPackType": "VlocityLookupMatchingKeyObject",
            "VlocityLookupRecordSourceKey": "%vlocity_namespace%__Attribute__c/B2CCmex_ATTR_HASDISCOUNT_CHAR",
            "VlocityRecordSObjectType": "%vlocity_namespace%__Attribute__c"
        },
        "%vlocity_namespace%__AttributeId__r.%vlocity_namespace%__Code__c": "B2CCmex_ATTR_HASDISCOUNT_CHAR",
        "%vlocity_namespace%__AttributeName__c": "HasDiscount",
        "%vlocity_namespace%__ConfigurationDetail__c": "",
        "%vlocity_namespace%__ConfigurationStages__c": "",
        "%vlocity_namespace%__CustomConfigUiTemplate__c": "",
        "%vlocity_namespace%__Data__c": "",
        "%vlocity_namespace%__DefaultPicklistEntryId__c": "",
        "%vlocity_namespace%__DefaultPicklistValueId__c": "",
        "%vlocity_namespace%__DisplaySequence__c": "103",
        "%vlocity_namespace%__EndStory__c": "",
        "%vlocity_namespace%__ExcludedPicklistEntryIds__c": "",
        "%vlocity_namespace%__ExcludedPicklistValues__c": "",
        "%vlocity_namespace%__FormatMask__c": "",
        "%vlocity_namespace%__GlobalKey__c": "2421e4c6-c9a9-b330-5bd6-b467572ac7d7",
        "%vlocity_namespace%__HasRule__c": false,
        "%vlocity_namespace%__HelpText__c": "",
        "%vlocity_namespace%__IsActiveAssignment__c": true,
        "%vlocity_namespace%__IsConfigurable__c": true,
        "%vlocity_namespace%__IsDynamic__c": false,
        "%vlocity_namespace%__IsEncrypted__c": false,
        "%vlocity_namespace%__IsHidden__c": false,
        "%vlocity_namespace%__IsNotAssetizable__c": false,
        "%vlocity_namespace%__IsNotTranslatable__c": false,
        "%vlocity_namespace%__IsOverride__c": false,
        "%vlocity_namespace%__IsQueryDriven__c": false,
        "%vlocity_namespace%__IsReadOnly__c": false,
        "%vlocity_namespace%__IsRequired__c": false,
        "%vlocity_namespace%__LookupFilter__c": "",
        "%vlocity_namespace%__LookupObjectId__c": "",
        "%vlocity_namespace%__LookupObjectTypeId__c": "",
        "%vlocity_namespace%__ObjectId__c": {
            "%vlocity_namespace%__GlobalKey__c": "4def5a99-88c1-e52a-bb07-8027a24de5db",
            "VlocityDataPackType": "VlocityMatchingKeyObject",
            "VlocityMatchingRecordSourceKey": "Product2/4def5a99-88c1-e52a-bb07-8027a24de5db",
            "VlocityRecordSObjectType": "Product2"
        },
        "%vlocity_namespace%__ObjectType__c": "%vlocity_namespace%__ObjectClass__c",
        "%vlocity_namespace%__OverrideContext__c": "",
        "%vlocity_namespace%__PicklistId__c": "",
        "%vlocity_namespace%__QueryCode__c": "",
        "%vlocity_namespace%__QueryLabel__c": "",
        "%vlocity_namespace%__RemoveDate__c": "",
        "%vlocity_namespace%__RemovedFlag__c": false,
        "%vlocity_namespace%__RuleData__c": "",
        "%vlocity_namespace%__RuleMessage__c": "",
        "%vlocity_namespace%__StartStory__c": "",
        "%vlocity_namespace%__StyleClass__c": "",
        "%vlocity_namespace%__UIDisplayType__c": "",
        "%vlocity_namespace%__ValidValuesData__c": "",
        "%vlocity_namespace%__ValueDataType__c": "Checkbox",
        "%vlocity_namespace%__ValueDecoder__c": "",
        "%vlocity_namespace%__ValueDescription__c": "",
        "%vlocity_namespace%__Value__c": "false",
        "Name": "CLONED_01t4W00000CT8lZQAT_B2CCmex_ATTR_HASDISCOUNT_CHAR",
        "VlocityDataPackType": "SObject",
        "VlocityRecordSObjectType": "%vlocity_namespace%__AttributeAssignment__c",
        "VlocityRecordSourceKey": "%vlocity_namespace%__AttributeAssignment__c/2421e4c6-c9a9-b330-5bd6-b467572ac7d7"
    },
    {
        "%vlocity_namespace%__AddDate__c": "",
        "%vlocity_namespace%__AttributeAdjustmentComments__c": "",
        "%vlocity_namespace%__AttributeAdjustmentUnits__c": "",
        "%vlocity_namespace%__AttributeCategoryId__c": {
            "%vlocity_namespace%__Code__c": "B2CCmex_ATC_CHARACTERISTIC",
            "VlocityDataPackType": "VlocityLookupMatchingKeyObject",
            "VlocityLookupRecordSourceKey": "%vlocity_namespace%__AttributeCategory__c/B2CCmex_ATC_CHARACTERISTIC",
            "VlocityRecordSObjectType": "%vlocity_namespace%__AttributeCategory__c"
        },
        "%vlocity_namespace%__AttributeDisplayNameOverride__c": "Tangible",
        "%vlocity_namespace%__AttributeDisplaySequence__c": "16",
        "%vlocity_namespace%__AttributeId__c": {
            "%vlocity_namespace%__Code__c": "B2CCmex_ATTR_TANGIBLE_CHAR",
            "VlocityDataPackType": "VlocityLookupMatchingKeyObject",
            "VlocityLookupRecordSourceKey": "%vlocity_namespace%__Attribute__c/B2CCmex_ATTR_TANGIBLE_CHAR",
            "VlocityRecordSObjectType": "%vlocity_namespace%__Attribute__c"
        },
        "%vlocity_namespace%__AttributeId__r.%vlocity_namespace%__Code__c": "B2CCmex_ATTR_TANGIBLE_CHAR",
        "%vlocity_namespace%__AttributeName__c": "Tangible",
        "%vlocity_namespace%__ConfigurationDetail__c": "",
        "%vlocity_namespace%__ConfigurationStages__c": "",
        "%vlocity_namespace%__CustomConfigUiTemplate__c": "",
        "%vlocity_namespace%__Data__c": "",
        "%vlocity_namespace%__DefaultPicklistEntryId__c": "",
        "%vlocity_namespace%__DefaultPicklistValueId__c": "",
        "%vlocity_namespace%__DisplaySequence__c": "null",
        "%vlocity_namespace%__EndStory__c": "",
        "%vlocity_namespace%__ExcludedPicklistEntryIds__c": "",
        "%vlocity_namespace%__ExcludedPicklistValues__c": "",
        "%vlocity_namespace%__FormatMask__c": "",
        "%vlocity_namespace%__GlobalKey__c": "8730f9ce-0c1e-d56f-58dc-2773a46ec0c9",
        "%vlocity_namespace%__HasRule__c": false,
        "%vlocity_namespace%__HelpText__c": "",
        "%vlocity_namespace%__IsActiveAssignment__c": true,
        "%vlocity_namespace%__IsConfigurable__c": true,
        "%vlocity_namespace%__IsDynamic__c": false,
        "%vlocity_namespace%__IsEncrypted__c": false,
        "%vlocity_namespace%__IsHidden__c": false,
        "%vlocity_namespace%__IsNotAssetizable__c": false,
        "%vlocity_namespace%__IsNotTranslatable__c": false,
        "%vlocity_namespace%__IsOverride__c": false,
        "%vlocity_namespace%__IsQueryDriven__c": false,
        "%vlocity_namespace%__IsReadOnly__c": false,
        "%vlocity_namespace%__IsRequired__c": false,
        "%vlocity_namespace%__LookupFilter__c": "",
        "%vlocity_namespace%__LookupObjectId__c": "",
        "%vlocity_namespace%__LookupObjectTypeId__c": "",
        "%vlocity_namespace%__ObjectId__c": {
            "%vlocity_namespace%__GlobalKey__c": "4def5a99-88c1-e52a-bb07-8027a24de5db",
            "VlocityDataPackType": "VlocityMatchingKeyObject",
            "VlocityMatchingRecordSourceKey": "Product2/4def5a99-88c1-e52a-bb07-8027a24de5db",
            "VlocityRecordSObjectType": "Product2"
        },
        "%vlocity_namespace%__ObjectType__c": "Product2",
        "%vlocity_namespace%__OverrideContext__c": "",
        "%vlocity_namespace%__PicklistId__c": "",
        "%vlocity_namespace%__QueryCode__c": "",
        "%vlocity_namespace%__QueryLabel__c": "",
        "%vlocity_namespace%__RemoveDate__c": "",
        "%vlocity_namespace%__RemovedFlag__c": false,
        "%vlocity_namespace%__RuleData__c": "",
        "%vlocity_namespace%__RuleMessage__c": "",
        "%vlocity_namespace%__StartStory__c": "",
        "%vlocity_namespace%__StyleClass__c": "",
        "%vlocity_namespace%__UIDisplayType__c": "",
        "%vlocity_namespace%__ValidValuesData__c": "",
        "%vlocity_namespace%__ValueDataType__c": "Checkbox",
        "%vlocity_namespace%__ValueDecoder__c": "",
        "%vlocity_namespace%__ValueDescription__c": "",
        "%vlocity_namespace%__Value__c": "false",
        "Name": "TempAA-B2CCmex_ATTR_ TANGIBLE_CHAR",
        "VlocityDataPackType": "SObject",
        "VlocityRecordSObjectType": "%vlocity_namespace%__AttributeAssignment__c",
        "VlocityRecordSourceKey": "%vlocity_namespace%__AttributeAssignment__c/8730f9ce-0c1e-d56f-58dc-2773a46ec0c9"
    },
    {
        "%vlocity_namespace%__AddDate__c": "",
        "%vlocity_namespace%__AttributeAdjustmentComments__c": "",
        "%vlocity_namespace%__AttributeAdjustmentUnits__c": "",
        "%vlocity_namespace%__AttributeCategoryId__c": {
            "%vlocity_namespace%__Code__c": "B2CCmex_ATC_FEATURES",
            "VlocityDataPackType": "VlocityLookupMatchingKeyObject",
            "VlocityLookupRecordSourceKey": "%vlocity_namespace%__AttributeCategory__c/B2CCmex_ATC_FEATURES",
            "VlocityRecordSObjectType": "%vlocity_namespace%__AttributeCategory__c"
        },
        "%vlocity_namespace%__AttributeDisplayNameOverride__c": "Adult Filter",
        "%vlocity_namespace%__AttributeDisplaySequence__c": "11",
        "%vlocity_namespace%__AttributeId__c": {
            "%vlocity_namespace%__Code__c": "B2CCmex_ATTR_ADULT_FILTER_FEAT",
            "VlocityDataPackType": "VlocityLookupMatchingKeyObject",
            "VlocityLookupRecordSourceKey": "%vlocity_namespace%__Attribute__c/B2CCmex_ATTR_ADULT_FILTER_FEAT",
            "VlocityRecordSObjectType": "%vlocity_namespace%__Attribute__c"
        },
        "%vlocity_namespace%__AttributeId__r.%vlocity_namespace%__Code__c": "B2CCmex_ATTR_ADULT_FILTER_FEAT",
        "%vlocity_namespace%__AttributeName__c": "Adult Filter",
        "%vlocity_namespace%__ConfigurationDetail__c": "",
        "%vlocity_namespace%__ConfigurationStages__c": "",
        "%vlocity_namespace%__CustomConfigUiTemplate__c": "",
        "%vlocity_namespace%__Data__c": "",
        "%vlocity_namespace%__DefaultPicklistEntryId__c": "",
        "%vlocity_namespace%__DefaultPicklistValueId__c": "",
        "%vlocity_namespace%__DisplaySequence__c": "null",
        "%vlocity_namespace%__EndStory__c": "",
        "%vlocity_namespace%__ExcludedPicklistEntryIds__c": "",
        "%vlocity_namespace%__ExcludedPicklistValues__c": "",
        "%vlocity_namespace%__FormatMask__c": "",
        "%vlocity_namespace%__GlobalKey__c": "f3eab0af-3fb8-c880-dc43-f7ddee825cda",
        "%vlocity_namespace%__HasRule__c": false,
        "%vlocity_namespace%__HelpText__c": "",
        "%vlocity_namespace%__IsActiveAssignment__c": true,
        "%vlocity_namespace%__IsConfigurable__c": true,
        "%vlocity_namespace%__IsDynamic__c": false,
        "%vlocity_namespace%__IsEncrypted__c": false,
        "%vlocity_namespace%__IsHidden__c": false,
        "%vlocity_namespace%__IsNotAssetizable__c": false,
        "%vlocity_namespace%__IsNotTranslatable__c": false,
        "%vlocity_namespace%__IsOverride__c": false,
        "%vlocity_namespace%__IsQueryDriven__c": false,
        "%vlocity_namespace%__IsReadOnly__c": false,
        "%vlocity_namespace%__IsRequired__c": false,
        "%vlocity_namespace%__LookupFilter__c": "",
        "%vlocity_namespace%__LookupObjectId__c": "",
        "%vlocity_namespace%__LookupObjectTypeId__c": "",
        "%vlocity_namespace%__ObjectId__c": {
            "%vlocity_namespace%__GlobalKey__c": "4def5a99-88c1-e52a-bb07-8027a24de5db",
            "VlocityDataPackType": "VlocityMatchingKeyObject",
            "VlocityMatchingRecordSourceKey": "Product2/4def5a99-88c1-e52a-bb07-8027a24de5db",
            "VlocityRecordSObjectType": "Product2"
        },
        "%vlocity_namespace%__ObjectType__c": "Product2",
        "%vlocity_namespace%__OverrideContext__c": "",
        "%vlocity_namespace%__PicklistId__c": "",
        "%vlocity_namespace%__QueryCode__c": "",
        "%vlocity_namespace%__QueryLabel__c": "",
        "%vlocity_namespace%__RemoveDate__c": "",
        "%vlocity_namespace%__RemovedFlag__c": false,
        "%vlocity_namespace%__RuleData__c": "",
        "%vlocity_namespace%__RuleMessage__c": "",
        "%vlocity_namespace%__StartStory__c": "",
        "%vlocity_namespace%__StyleClass__c": "",
        "%vlocity_namespace%__UIDisplayType__c": "",
        "%vlocity_namespace%__ValidValuesData__c": "",
        "%vlocity_namespace%__ValueDataType__c": "Checkbox",
        "%vlocity_namespace%__ValueDecoder__c": "",
        "%vlocity_namespace%__ValueDescription__c": "",
        "%vlocity_namespace%__Value__c": "false",
        "Name": "TempAA-B2CCmex_ATTR_ADULT_FILTER_FEAT",
        "VlocityDataPackType": "SObject",
        "VlocityRecordSObjectType": "%vlocity_namespace%__AttributeAssignment__c",
        "VlocityRecordSourceKey": "%vlocity_namespace%__AttributeAssignment__c/f3eab0af-3fb8-c880-dc43-f7ddee825cda"
    },
    {
        "%vlocity_namespace%__AddDate__c": "",
        "%vlocity_namespace%__AttributeAdjustmentComments__c": "",
        "%vlocity_namespace%__AttributeAdjustmentUnits__c": "",
        "%vlocity_namespace%__AttributeCategoryId__c": {
            "%vlocity_namespace%__Code__c": "B2CCmex_ATC_FEATURES",
            "VlocityDataPackType": "VlocityLookupMatchingKeyObject",
            "VlocityLookupRecordSourceKey": "%vlocity_namespace%__AttributeCategory__c/B2CCmex_ATC_FEATURES",
            "VlocityRecordSObjectType": "%vlocity_namespace%__AttributeCategory__c"
        },
        "%vlocity_namespace%__AttributeDisplayNameOverride__c": "Call Waiting",
        "%vlocity_namespace%__AttributeDisplaySequence__c": "12",
        "%vlocity_namespace%__AttributeId__c": {
            "%vlocity_namespace%__Code__c": "B2CCmex_ATTR_CALL_WAITING_FEAT",
            "VlocityDataPackType": "VlocityLookupMatchingKeyObject",
            "VlocityLookupRecordSourceKey": "%vlocity_namespace%__Attribute__c/B2CCmex_ATTR_CALL_WAITING_FEAT",
            "VlocityRecordSObjectType": "%vlocity_namespace%__Attribute__c"
        },
        "%vlocity_namespace%__AttributeId__r.%vlocity_namespace%__Code__c": "B2CCmex_ATTR_CALL_WAITING_FEAT",
        "%vlocity_namespace%__AttributeName__c": "Call Waiting",
        "%vlocity_namespace%__ConfigurationDetail__c": "",
        "%vlocity_namespace%__ConfigurationStages__c": "",
        "%vlocity_namespace%__CustomConfigUiTemplate__c": "",
        "%vlocity_namespace%__Data__c": "",
        "%vlocity_namespace%__DefaultPicklistEntryId__c": "",
        "%vlocity_namespace%__DefaultPicklistValueId__c": "",
        "%vlocity_namespace%__DisplaySequence__c": "null",
        "%vlocity_namespace%__EndStory__c": "",
        "%vlocity_namespace%__ExcludedPicklistEntryIds__c": "",
        "%vlocity_namespace%__ExcludedPicklistValues__c": "",
        "%vlocity_namespace%__FormatMask__c": "",
        "%vlocity_namespace%__GlobalKey__c": "e5396e0d-7fb6-10c0-8574-0ac7440a41b9",
        "%vlocity_namespace%__HasRule__c": false,
        "%vlocity_namespace%__HelpText__c": "",
        "%vlocity_namespace%__IsActiveAssignment__c": true,
        "%vlocity_namespace%__IsConfigurable__c": true,
        "%vlocity_namespace%__IsDynamic__c": false,
        "%vlocity_namespace%__IsEncrypted__c": false,
        "%vlocity_namespace%__IsHidden__c": false,
        "%vlocity_namespace%__IsNotAssetizable__c": false,
        "%vlocity_namespace%__IsNotTranslatable__c": false,
        "%vlocity_namespace%__IsOverride__c": false,
        "%vlocity_namespace%__IsQueryDriven__c": false,
        "%vlocity_namespace%__IsReadOnly__c": false,
        "%vlocity_namespace%__IsRequired__c": false,
        "%vlocity_namespace%__LookupFilter__c": "",
        "%vlocity_namespace%__LookupObjectId__c": "",
        "%vlocity_namespace%__LookupObjectTypeId__c": "",
        "%vlocity_namespace%__ObjectId__c": {
            "%vlocity_namespace%__GlobalKey__c": "4def5a99-88c1-e52a-bb07-8027a24de5db",
            "VlocityDataPackType": "VlocityMatchingKeyObject",
            "VlocityMatchingRecordSourceKey": "Product2/4def5a99-88c1-e52a-bb07-8027a24de5db",
            "VlocityRecordSObjectType": "Product2"
        },
        "%vlocity_namespace%__ObjectType__c": "Product2",
        "%vlocity_namespace%__OverrideContext__c": "",
        "%vlocity_namespace%__PicklistId__c": "",
        "%vlocity_namespace%__QueryCode__c": "",
        "%vlocity_namespace%__QueryLabel__c": "",
        "%vlocity_namespace%__RemoveDate__c": "",
        "%vlocity_namespace%__RemovedFlag__c": false,
        "%vlocity_namespace%__RuleData__c": "",
        "%vlocity_namespace%__RuleMessage__c": "",
        "%vlocity_namespace%__StartStory__c": "",
        "%vlocity_namespace%__StyleClass__c": "",
        "%vlocity_namespace%__UIDisplayType__c": "",
        "%vlocity_namespace%__ValidValuesData__c": "",
        "%vlocity_namespace%__ValueDataType__c": "Checkbox",
        "%vlocity_namespace%__ValueDecoder__c": "",
        "%vlocity_namespace%__ValueDescription__c": "",
        "%vlocity_namespace%__Value__c": "true",
        "Name": "TempAA-B2CCmex_ATTR_CALL_WAITING_FEAT",
        "VlocityDataPackType": "SObject",
        "VlocityRecordSObjectType": "%vlocity_namespace%__AttributeAssignment__c",
        "VlocityRecordSourceKey": "%vlocity_namespace%__AttributeAssignment__c/e5396e0d-7fb6-10c0-8574-0ac7440a41b9"
    },
    {
        "%vlocity_namespace%__AddDate__c": "",
        "%vlocity_namespace%__AttributeAdjustmentComments__c": "",
        "%vlocity_namespace%__AttributeAdjustmentUnits__c": "",
        "%vlocity_namespace%__AttributeCategoryId__c": {
            "%vlocity_namespace%__Code__c": "B2CCmex_ATC_FEATURES",
            "VlocityDataPackType": "VlocityLookupMatchingKeyObject",
            "VlocityLookupRecordSourceKey": "%vlocity_namespace%__AttributeCategory__c/B2CCmex_ATC_FEATURES",
            "VlocityRecordSObjectType": "%vlocity_namespace%__AttributeCategory__c"
        },
        "%vlocity_namespace%__AttributeDisplayNameOverride__c": "Caller Id",
        "%vlocity_namespace%__AttributeDisplaySequence__c": "13",
        "%vlocity_namespace%__AttributeId__c": {
            "%vlocity_namespace%__Code__c": "B2CCmex_ATTR_CALLER_ID_FEAT",
            "VlocityDataPackType": "VlocityLookupMatchingKeyObject",
            "VlocityLookupRecordSourceKey": "%vlocity_namespace%__Attribute__c/B2CCmex_ATTR_CALLER_ID_FEAT",
            "VlocityRecordSObjectType": "%vlocity_namespace%__Attribute__c"
        },
        "%vlocity_namespace%__AttributeId__r.%vlocity_namespace%__Code__c": "B2CCmex_ATTR_CALLER_ID_FEAT",
        "%vlocity_namespace%__AttributeName__c": "Caller Id",
        "%vlocity_namespace%__ConfigurationDetail__c": "",
        "%vlocity_namespace%__ConfigurationStages__c": "",
        "%vlocity_namespace%__CustomConfigUiTemplate__c": "",
        "%vlocity_namespace%__Data__c": "",
        "%vlocity_namespace%__DefaultPicklistEntryId__c": "",
        "%vlocity_namespace%__DefaultPicklistValueId__c": "",
        "%vlocity_namespace%__DisplaySequence__c": "1000",
        "%vlocity_namespace%__EndStory__c": "",
        "%vlocity_namespace%__ExcludedPicklistEntryIds__c": "",
        "%vlocity_namespace%__ExcludedPicklistValues__c": "",
        "%vlocity_namespace%__FormatMask__c": "",
        "%vlocity_namespace%__GlobalKey__c": "122b8066-11b7-9ca5-bd80-ad50562a4b27",
        "%vlocity_namespace%__HasRule__c": false,
        "%vlocity_namespace%__HelpText__c": "",
        "%vlocity_namespace%__IsActiveAssignment__c": true,
        "%vlocity_namespace%__IsConfigurable__c": true,
        "%vlocity_namespace%__IsDynamic__c": false,
        "%vlocity_namespace%__IsEncrypted__c": false,
        "%vlocity_namespace%__IsHidden__c": false,
        "%vlocity_namespace%__IsNotAssetizable__c": false,
        "%vlocity_namespace%__IsNotTranslatable__c": false,
        "%vlocity_namespace%__IsOverride__c": false,
        "%vlocity_namespace%__IsQueryDriven__c": false,
        "%vlocity_namespace%__IsReadOnly__c": false,
        "%vlocity_namespace%__IsRequired__c": false,
        "%vlocity_namespace%__LookupFilter__c": "",
        "%vlocity_namespace%__LookupObjectId__c": "",
        "%vlocity_namespace%__LookupObjectTypeId__c": "",
        "%vlocity_namespace%__ObjectId__c": {
            "%vlocity_namespace%__GlobalKey__c": "4def5a99-88c1-e52a-bb07-8027a24de5db",
            "VlocityDataPackType": "VlocityMatchingKeyObject",
            "VlocityMatchingRecordSourceKey": "Product2/4def5a99-88c1-e52a-bb07-8027a24de5db",
            "VlocityRecordSObjectType": "Product2"
        },
        "%vlocity_namespace%__ObjectType__c": "%vlocity_namespace%__ObjectClass__c",
        "%vlocity_namespace%__OverrideContext__c": "",
        "%vlocity_namespace%__PicklistId__c": "",
        "%vlocity_namespace%__QueryCode__c": "",
        "%vlocity_namespace%__QueryLabel__c": "",
        "%vlocity_namespace%__RemoveDate__c": "",
        "%vlocity_namespace%__RemovedFlag__c": false,
        "%vlocity_namespace%__RuleData__c": "",
        "%vlocity_namespace%__RuleMessage__c": "",
        "%vlocity_namespace%__StartStory__c": "",
        "%vlocity_namespace%__StyleClass__c": "",
        "%vlocity_namespace%__UIDisplayType__c": "",
        "%vlocity_namespace%__ValidValuesData__c": "",
        "%vlocity_namespace%__ValueDataType__c": "Checkbox",
        "%vlocity_namespace%__ValueDecoder__c": "",
        "%vlocity_namespace%__ValueDescription__c": "",
        "%vlocity_namespace%__Value__c": "",
        "Name": "CLONED_01t4x000000BfPfAAK_B2CCmex_ATTR_CALLER_ID_FEAT",
        "VlocityDataPackType": "SObject",
        "VlocityRecordSObjectType": "%vlocity_namespace%__AttributeAssignment__c",
        "VlocityRecordSourceKey": "%vlocity_namespace%__AttributeAssignment__c/122b8066-11b7-9ca5-bd80-ad50562a4b27"
    },
    {
        "%vlocity_namespace%__AddDate__c": "",
        "%vlocity_namespace%__AttributeAdjustmentComments__c": "",
        "%vlocity_namespace%__AttributeAdjustmentUnits__c": "",
        "%vlocity_namespace%__AttributeCategoryId__c": {
            "%vlocity_namespace%__Code__c": "B2CCmex_ATC_FEATURES",
            "VlocityDataPackType": "VlocityLookupMatchingKeyObject",
            "VlocityLookupRecordSourceKey": "%vlocity_namespace%__AttributeCategory__c/B2CCmex_ATC_FEATURES",
            "VlocityRecordSObjectType": "%vlocity_namespace%__AttributeCategory__c"
        },
        "%vlocity_namespace%__AttributeDisplayNameOverride__c": "International Calling",
        "%vlocity_namespace%__AttributeDisplaySequence__c": "14",
        "%vlocity_namespace%__AttributeId__c": {
            "%vlocity_namespace%__Code__c": "B2CCmex_ATTR_INTERNATIONAL_CALLING_FEAT",
            "VlocityDataPackType": "VlocityLookupMatchingKeyObject",
            "VlocityLookupRecordSourceKey": "%vlocity_namespace%__Attribute__c/B2CCmex_ATTR_INTERNATIONAL_CALLING_FEAT",
            "VlocityRecordSObjectType": "%vlocity_namespace%__Attribute__c"
        },
        "%vlocity_namespace%__AttributeId__r.%vlocity_namespace%__Code__c": "B2CCmex_ATTR_INTERNATIONAL_CALLING_FEAT",
        "%vlocity_namespace%__AttributeName__c": "International Calling",
        "%vlocity_namespace%__ConfigurationDetail__c": "",
        "%vlocity_namespace%__ConfigurationStages__c": "",
        "%vlocity_namespace%__CustomConfigUiTemplate__c": "",
        "%vlocity_namespace%__Data__c": "",
        "%vlocity_namespace%__DefaultPicklistEntryId__c": "",
        "%vlocity_namespace%__DefaultPicklistValueId__c": "",
        "%vlocity_namespace%__DisplaySequence__c": "null",
        "%vlocity_namespace%__EndStory__c": "",
        "%vlocity_namespace%__ExcludedPicklistEntryIds__c": "",
        "%vlocity_namespace%__ExcludedPicklistValues__c": "",
        "%vlocity_namespace%__FormatMask__c": "",
        "%vlocity_namespace%__GlobalKey__c": "dcca6407-bee4-b48d-c4c3-5a009457d399",
        "%vlocity_namespace%__HasRule__c": false,
        "%vlocity_namespace%__HelpText__c": "",
        "%vlocity_namespace%__IsActiveAssignment__c": true,
        "%vlocity_namespace%__IsConfigurable__c": true,
        "%vlocity_namespace%__IsDynamic__c": false,
        "%vlocity_namespace%__IsEncrypted__c": false,
        "%vlocity_namespace%__IsHidden__c": false,
        "%vlocity_namespace%__IsNotAssetizable__c": false,
        "%vlocity_namespace%__IsNotTranslatable__c": false,
        "%vlocity_namespace%__IsOverride__c": false,
        "%vlocity_namespace%__IsQueryDriven__c": false,
        "%vlocity_namespace%__IsReadOnly__c": false,
        "%vlocity_namespace%__IsRequired__c": false,
        "%vlocity_namespace%__LookupFilter__c": "",
        "%vlocity_namespace%__LookupObjectId__c": "",
        "%vlocity_namespace%__LookupObjectTypeId__c": "",
        "%vlocity_namespace%__ObjectId__c": {
            "%vlocity_namespace%__GlobalKey__c": "4def5a99-88c1-e52a-bb07-8027a24de5db",
            "VlocityDataPackType": "VlocityMatchingKeyObject",
            "VlocityMatchingRecordSourceKey": "Product2/4def5a99-88c1-e52a-bb07-8027a24de5db",
            "VlocityRecordSObjectType": "Product2"
        },
        "%vlocity_namespace%__ObjectType__c": "Product2",
        "%vlocity_namespace%__OverrideContext__c": "",
        "%vlocity_namespace%__PicklistId__c": "",
        "%vlocity_namespace%__QueryCode__c": "",
        "%vlocity_namespace%__QueryLabel__c": "",
        "%vlocity_namespace%__RemoveDate__c": "",
        "%vlocity_namespace%__RemovedFlag__c": false,
        "%vlocity_namespace%__RuleData__c": "",
        "%vlocity_namespace%__RuleMessage__c": "",
        "%vlocity_namespace%__StartStory__c": "",
        "%vlocity_namespace%__StyleClass__c": "",
        "%vlocity_namespace%__UIDisplayType__c": "",
        "%vlocity_namespace%__ValidValuesData__c": "",
        "%vlocity_namespace%__ValueDataType__c": "Checkbox",
        "%vlocity_namespace%__ValueDecoder__c": "",
        "%vlocity_namespace%__ValueDescription__c": "",
        "%vlocity_namespace%__Value__c": "true",
        "Name": "TempAA-B2CCmex_ATTR_INTERNATIONAL_CALLING_CHAR",
        "VlocityDataPackType": "SObject",
        "VlocityRecordSObjectType": "%vlocity_namespace%__AttributeAssignment__c",
        "VlocityRecordSourceKey": "%vlocity_namespace%__AttributeAssignment__c/dcca6407-bee4-b48d-c4c3-5a009457d399"
    },
    {
        "%vlocity_namespace%__AddDate__c": "",
        "%vlocity_namespace%__AttributeAdjustmentComments__c": "",
        "%vlocity_namespace%__AttributeAdjustmentUnits__c": "",
        "%vlocity_namespace%__AttributeCategoryId__c": {
            "%vlocity_namespace%__Code__c": "B2CCmex_ATC_FEATURES",
            "VlocityDataPackType": "VlocityLookupMatchingKeyObject",
            "VlocityLookupRecordSourceKey": "%vlocity_namespace%__AttributeCategory__c/B2CCmex_ATC_FEATURES",
            "VlocityRecordSObjectType": "%vlocity_namespace%__AttributeCategory__c"
        },
        "%vlocity_namespace%__AttributeDisplayNameOverride__c": "Roaming",
        "%vlocity_namespace%__AttributeDisplaySequence__c": "15",
        "%vlocity_namespace%__AttributeId__c": {
            "%vlocity_namespace%__Code__c": "B2CCmex_ATTR_ROAMING_FEAT",
            "VlocityDataPackType": "VlocityLookupMatchingKeyObject",
            "VlocityLookupRecordSourceKey": "%vlocity_namespace%__Attribute__c/B2CCmex_ATTR_ROAMING_FEAT",
            "VlocityRecordSObjectType": "%vlocity_namespace%__Attribute__c"
        },
        "%vlocity_namespace%__AttributeId__r.%vlocity_namespace%__Code__c": "B2CCmex_ATTR_ROAMING_FEAT",
        "%vlocity_namespace%__AttributeName__c": "Roaming",
        "%vlocity_namespace%__ConfigurationDetail__c": "",
        "%vlocity_namespace%__ConfigurationStages__c": "",
        "%vlocity_namespace%__CustomConfigUiTemplate__c": "",
        "%vlocity_namespace%__Data__c": "",
        "%vlocity_namespace%__DefaultPicklistEntryId__c": "",
        "%vlocity_namespace%__DefaultPicklistValueId__c": "",
        "%vlocity_namespace%__DisplaySequence__c": "null",
        "%vlocity_namespace%__EndStory__c": "",
        "%vlocity_namespace%__ExcludedPicklistEntryIds__c": "",
        "%vlocity_namespace%__ExcludedPicklistValues__c": "",
        "%vlocity_namespace%__FormatMask__c": "",
        "%vlocity_namespace%__GlobalKey__c": "61307ffe-c2a9-52ff-f4ac-c61f5936570a",
        "%vlocity_namespace%__HasRule__c": false,
        "%vlocity_namespace%__HelpText__c": "",
        "%vlocity_namespace%__IsActiveAssignment__c": true,
        "%vlocity_namespace%__IsConfigurable__c": true,
        "%vlocity_namespace%__IsDynamic__c": false,
        "%vlocity_namespace%__IsEncrypted__c": false,
        "%vlocity_namespace%__IsHidden__c": false,
        "%vlocity_namespace%__IsNotAssetizable__c": false,
        "%vlocity_namespace%__IsNotTranslatable__c": false,
        "%vlocity_namespace%__IsOverride__c": false,
        "%vlocity_namespace%__IsQueryDriven__c": false,
        "%vlocity_namespace%__IsReadOnly__c": false,
        "%vlocity_namespace%__IsRequired__c": false,
        "%vlocity_namespace%__LookupFilter__c": "",
        "%vlocity_namespace%__LookupObjectId__c": "",
        "%vlocity_namespace%__LookupObjectTypeId__c": "",
        "%vlocity_namespace%__ObjectId__c": {
            "%vlocity_namespace%__GlobalKey__c": "4def5a99-88c1-e52a-bb07-8027a24de5db",
            "VlocityDataPackType": "VlocityMatchingKeyObject",
            "VlocityMatchingRecordSourceKey": "Product2/4def5a99-88c1-e52a-bb07-8027a24de5db",
            "VlocityRecordSObjectType": "Product2"
        },
        "%vlocity_namespace%__ObjectType__c": "Product2",
        "%vlocity_namespace%__OverrideContext__c": "",
        "%vlocity_namespace%__PicklistId__c": "",
        "%vlocity_namespace%__QueryCode__c": "",
        "%vlocity_namespace%__QueryLabel__c": "",
        "%vlocity_namespace%__RemoveDate__c": "",
        "%vlocity_namespace%__RemovedFlag__c": false,
        "%vlocity_namespace%__RuleData__c": "",
        "%vlocity_namespace%__RuleMessage__c": "",
        "%vlocity_namespace%__StartStory__c": "",
        "%vlocity_namespace%__StyleClass__c": "",
        "%vlocity_namespace%__UIDisplayType__c": "",
        "%vlocity_namespace%__ValidValuesData__c": "",
        "%vlocity_namespace%__ValueDataType__c": "Checkbox",
        "%vlocity_namespace%__ValueDecoder__c": "",
        "%vlocity_namespace%__ValueDescription__c": "",
        "%vlocity_namespace%__Value__c": "true",
        "Name": "TempAA-B2CCmex_ATTR_ROAMING",
        "VlocityDataPackType": "SObject",
        "VlocityRecordSObjectType": "%vlocity_namespace%__AttributeAssignment__c",
        "VlocityRecordSourceKey": "%vlocity_namespace%__AttributeAssignment__c/61307ffe-c2a9-52ff-f4ac-c61f5936570a"
    },
    {
        "%vlocity_namespace%__AddDate__c": "",
        "%vlocity_namespace%__AttributeAdjustmentComments__c": "",
        "%vlocity_namespace%__AttributeAdjustmentUnits__c": "",
        "%vlocity_namespace%__AttributeCategoryId__c": {
            "%vlocity_namespace%__Code__c": "B2CCmex_ATC_FEATURES",
            "VlocityDataPackType": "VlocityLookupMatchingKeyObject",
            "VlocityLookupRecordSourceKey": "%vlocity_namespace%__AttributeCategory__c/B2CCmex_ATC_FEATURES",
            "VlocityRecordSObjectType": "%vlocity_namespace%__AttributeCategory__c"
        },
        "%vlocity_namespace%__AttributeDisplayNameOverride__c": "Test Features",
        "%vlocity_namespace%__AttributeDisplaySequence__c": "34",
        "%vlocity_namespace%__AttributeId__c": {
            "%vlocity_namespace%__Code__c": "Test_Features",
            "VlocityDataPackType": "VlocityLookupMatchingKeyObject",
            "VlocityLookupRecordSourceKey": "%vlocity_namespace%__Attribute__c/Test_Features",
            "VlocityRecordSObjectType": "%vlocity_namespace%__Attribute__c"
        },
        "%vlocity_namespace%__AttributeId__r.%vlocity_namespace%__Code__c": "Test_Features",
        "%vlocity_namespace%__AttributeName__c": "Test Features",
        "%vlocity_namespace%__ConfigurationDetail__c": "",
        "%vlocity_namespace%__ConfigurationStages__c": "",
        "%vlocity_namespace%__CustomConfigUiTemplate__c": "",
        "%vlocity_namespace%__Data__c": "",
        "%vlocity_namespace%__DefaultPicklistEntryId__c": "",
        "%vlocity_namespace%__DefaultPicklistValueId__c": "",
        "%vlocity_namespace%__DisplaySequence__c": "null",
        "%vlocity_namespace%__EndStory__c": "",
        "%vlocity_namespace%__ExcludedPicklistEntryIds__c": "",
        "%vlocity_namespace%__ExcludedPicklistValues__c": "",
        "%vlocity_namespace%__FormatMask__c": "",
        "%vlocity_namespace%__GlobalKey__c": "403add5d-6de7-fc1a-3536-13230d753af8",
        "%vlocity_namespace%__HasRule__c": false,
        "%vlocity_namespace%__HelpText__c": "",
        "%vlocity_namespace%__IsActiveAssignment__c": true,
        "%vlocity_namespace%__IsConfigurable__c": true,
        "%vlocity_namespace%__IsDynamic__c": false,
        "%vlocity_namespace%__IsEncrypted__c": false,
        "%vlocity_namespace%__IsHidden__c": false,
        "%vlocity_namespace%__IsNotAssetizable__c": false,
        "%vlocity_namespace%__IsNotTranslatable__c": false,
        "%vlocity_namespace%__IsOverride__c": false,
        "%vlocity_namespace%__IsQueryDriven__c": false,
        "%vlocity_namespace%__IsReadOnly__c": false,
        "%vlocity_namespace%__IsRequired__c": false,
        "%vlocity_namespace%__LookupFilter__c": "",
        "%vlocity_namespace%__LookupObjectId__c": "",
        "%vlocity_namespace%__LookupObjectTypeId__c": "",
        "%vlocity_namespace%__ObjectId__c": {
            "%vlocity_namespace%__GlobalKey__c": "4def5a99-88c1-e52a-bb07-8027a24de5db",
            "VlocityDataPackType": "VlocityMatchingKeyObject",
            "VlocityMatchingRecordSourceKey": "Product2/4def5a99-88c1-e52a-bb07-8027a24de5db",
            "VlocityRecordSObjectType": "Product2"
        },
        "%vlocity_namespace%__ObjectType__c": "Product2",
        "%vlocity_namespace%__OverrideContext__c": "",
        "%vlocity_namespace%__PicklistId__c": "",
        "%vlocity_namespace%__QueryCode__c": "",
        "%vlocity_namespace%__QueryLabel__c": "",
        "%vlocity_namespace%__RemoveDate__c": "",
        "%vlocity_namespace%__RemovedFlag__c": false,
        "%vlocity_namespace%__RuleData__c": "",
        "%vlocity_namespace%__RuleMessage__c": "",
        "%vlocity_namespace%__StartStory__c": "",
        "%vlocity_namespace%__StyleClass__c": "",
        "%vlocity_namespace%__UIDisplayType__c": "",
        "%vlocity_namespace%__ValidValuesData__c": "",
        "%vlocity_namespace%__ValueDataType__c": "Checkbox",
        "%vlocity_namespace%__ValueDecoder__c": "",
        "%vlocity_namespace%__ValueDescription__c": "",
        "%vlocity_namespace%__Value__c": "true",
        "Name": "TempAA-Test_Features",
        "VlocityDataPackType": "SObject",
        "VlocityRecordSObjectType": "%vlocity_namespace%__AttributeAssignment__c",
        "VlocityRecordSourceKey": "%vlocity_namespace%__AttributeAssignment__c/403add5d-6de7-fc1a-3536-13230d753af8"
    },
    {
        "%vlocity_namespace%__AddDate__c": "",
        "%vlocity_namespace%__AttributeAdjustmentComments__c": "",
        "%vlocity_namespace%__AttributeAdjustmentUnits__c": "",
        "%vlocity_namespace%__AttributeCategoryId__c": {
            "%vlocity_namespace%__Code__c": "B2CCmex_ATC_FEATURES",
            "VlocityDataPackType": "VlocityLookupMatchingKeyObject",
            "VlocityLookupRecordSourceKey": "%vlocity_namespace%__AttributeCategory__c/B2CCmex_ATC_FEATURES",
            "VlocityRecordSObjectType": "%vlocity_namespace%__AttributeCategory__c"
        },
        "%vlocity_namespace%__AttributeDisplayNameOverride__c": "Voice Mail",
        "%vlocity_namespace%__AttributeDisplaySequence__c": "16",
        "%vlocity_namespace%__AttributeId__c": {
            "%vlocity_namespace%__Code__c": "B2CCmex_ATTR_VOICE_MAIL_FEAT",
            "VlocityDataPackType": "VlocityLookupMatchingKeyObject",
            "VlocityLookupRecordSourceKey": "%vlocity_namespace%__Attribute__c/B2CCmex_ATTR_VOICE_MAIL_FEAT",
            "VlocityRecordSObjectType": "%vlocity_namespace%__Attribute__c"
        },
        "%vlocity_namespace%__AttributeId__r.%vlocity_namespace%__Code__c": "B2CCmex_ATTR_VOICE_MAIL_FEAT",
        "%vlocity_namespace%__AttributeName__c": "Voice Mail",
        "%vlocity_namespace%__ConfigurationDetail__c": "",
        "%vlocity_namespace%__ConfigurationStages__c": "",
        "%vlocity_namespace%__CustomConfigUiTemplate__c": "",
        "%vlocity_namespace%__Data__c": "",
        "%vlocity_namespace%__DefaultPicklistEntryId__c": "",
        "%vlocity_namespace%__DefaultPicklistValueId__c": "",
        "%vlocity_namespace%__DisplaySequence__c": "1000",
        "%vlocity_namespace%__EndStory__c": "",
        "%vlocity_namespace%__ExcludedPicklistEntryIds__c": "",
        "%vlocity_namespace%__ExcludedPicklistValues__c": "",
        "%vlocity_namespace%__FormatMask__c": "",
        "%vlocity_namespace%__GlobalKey__c": "cc5bd30c-cdf0-3f27-2e7d-ea95bb983eca",
        "%vlocity_namespace%__HasRule__c": false,
        "%vlocity_namespace%__HelpText__c": "",
        "%vlocity_namespace%__IsActiveAssignment__c": true,
        "%vlocity_namespace%__IsConfigurable__c": true,
        "%vlocity_namespace%__IsDynamic__c": false,
        "%vlocity_namespace%__IsEncrypted__c": false,
        "%vlocity_namespace%__IsHidden__c": false,
        "%vlocity_namespace%__IsNotAssetizable__c": false,
        "%vlocity_namespace%__IsNotTranslatable__c": false,
        "%vlocity_namespace%__IsOverride__c": false,
        "%vlocity_namespace%__IsQueryDriven__c": false,
        "%vlocity_namespace%__IsReadOnly__c": false,
        "%vlocity_namespace%__IsRequired__c": false,
        "%vlocity_namespace%__LookupFilter__c": "",
        "%vlocity_namespace%__LookupObjectId__c": "",
        "%vlocity_namespace%__LookupObjectTypeId__c": "",
        "%vlocity_namespace%__ObjectId__c": {
            "%vlocity_namespace%__GlobalKey__c": "4def5a99-88c1-e52a-bb07-8027a24de5db",
            "VlocityDataPackType": "VlocityMatchingKeyObject",
            "VlocityMatchingRecordSourceKey": "Product2/4def5a99-88c1-e52a-bb07-8027a24de5db",
            "VlocityRecordSObjectType": "Product2"
        },
        "%vlocity_namespace%__ObjectType__c": "%vlocity_namespace%__ObjectClass__c",
        "%vlocity_namespace%__OverrideContext__c": "",
        "%vlocity_namespace%__PicklistId__c": "",
        "%vlocity_namespace%__QueryCode__c": "",
        "%vlocity_namespace%__QueryLabel__c": "",
        "%vlocity_namespace%__RemoveDate__c": "",
        "%vlocity_namespace%__RemovedFlag__c": false,
        "%vlocity_namespace%__RuleData__c": "",
        "%vlocity_namespace%__RuleMessage__c": "",
        "%vlocity_namespace%__StartStory__c": "",
        "%vlocity_namespace%__StyleClass__c": "",
        "%vlocity_namespace%__UIDisplayType__c": "",
        "%vlocity_namespace%__ValidValuesData__c": "",
        "%vlocity_namespace%__ValueDataType__c": "Checkbox",
        "%vlocity_namespace%__ValueDecoder__c": "",
        "%vlocity_namespace%__ValueDescription__c": "",
        "%vlocity_namespace%__Value__c": "",
        "Name": "CLONED_01t4x000000BfPfAAK_B2CCmex_ATTR_VOICE_MAIL_FEAT",
        "VlocityDataPackType": "SObject",
        "VlocityRecordSObjectType": "%vlocity_namespace%__AttributeAssignment__c",
        "VlocityRecordSourceKey": "%vlocity_namespace%__AttributeAssignment__c/cc5bd30c-cdf0-3f27-2e7d-ea95bb983eca"
    }
]